[
	{
		"name": "Martina A. Pope",
		"email": "ipsum@fringilla.com",
		"phone": "(155) 960-9429",
		"country": "Libya",
		"id": 1
	},
	{
		"name": "Guinevere Cobb",
		"email": "Suspendisse.sagittis@Nullamnisl.edu",
		"phone": "(716) 135-9994",
		"country": "Congo (Brazzaville)",
		"id": 2
	},
	{
		"name": "Lyle W. Hanson",
		"email": "Duis.mi@leo.net",
		"phone": "(527) 537-4398",
		"country": "Laos",
		"id": 3
	},
	{
		"name": "Amos Holmes",
		"email": "Nulla.aliquet.Proin@risusQuisque.co.uk",
		"phone": "(306) 892-3574",
		"country": "Cape Verde",
		"id": 4
	},
	{
		"name": "Kenneth E. Adkins",
		"email": "ut.odio.vel@Crasvehiculaaliquet.edu",
		"phone": "(674) 526-2209",
		"country": "Libya",
		"id": 5
	},
	{
		"name": "Christine U. Cherry",
		"email": "risus.odio.auctor@quam.edu",
		"phone": "(117) 757-1130",
		"country": "Angola",
		"id": 6
	},
	{
		"name": "Oprah Walton",
		"email": "luctus.aliquet@faucibusid.net",
		"phone": "(483) 335-5188",
		"country": "Viet Nam",
		"id": 7
	},
	{
		"name": "Alexander Sparks",
		"email": "turpis.Aliquam@loremsemper.co.uk",
		"phone": "(458) 297-7227",
		"country": "Honduras",
		"id": 8
	},
	{
		"name": "Hyacinth N. Chambers",
		"email": "amet.ante@diamloremauctor.net",
		"phone": "(328) 418-8761",
		"country": "Burkina Faso",
		"id": 9
	},
	{
		"name": "Doris Trevino",
		"email": "nibh.Donec.est@loremutaliquam.co.uk",
		"phone": "(475) 529-4735",
		"country": "Chad",
		"id": 10
	},
	{
		"name": "Camille Clarke",
		"email": "dignissim.lacus.Aliquam@nectempus.ca",
		"phone": "(658) 204-9808",
		"country": "Norfolk Island",
		"id": 11
	},
	{
		"name": "Ori Y. Park",
		"email": "sodales@imperdiet.net",
		"phone": "(617) 868-9801",
		"country": "Greece",
		"id": 12
	},
	{
		"name": "Rebecca H. Cummings",
		"email": "lorem@facilisis.ca",
		"phone": "(858) 771-5506",
		"country": "Uruguay",
		"id": 13
	},
	{
		"name": "Zephania G. Gonzales",
		"email": "aliquet@vel.com",
		"phone": "(691) 443-4816",
		"country": "Trinidad and Tobago",
		"id": 14
	},
	{
		"name": "Eaton L. Ayers",
		"email": "rutrum.Fusce@dolor.co.uk",
		"phone": "(951) 113-0080",
		"country": "Norfolk Island",
		"id": 15
	},
	{
		"name": "Neve A. Horn",
		"email": "sed@euduiCum.co.uk",
		"phone": "(984) 546-7063",
		"country": "Denmark",
		"id": 16
	},
	{
		"name": "Conan Stephenson",
		"email": "dis@loremDonec.com",
		"phone": "(568) 929-8548",
		"country": "Korea, South",
		"id": 17
	},
	{
		"name": "Jerome X. Knowles",
		"email": "lorem@luctus.org",
		"phone": "(544) 220-0298",
		"country": "Uzbekistan",
		"id": 18
	},
	{
		"name": "Elliott Levine",
		"email": "ipsum.primis@eu.org",
		"phone": "(737) 388-4470",
		"country": "Namibia",
		"id": 19
	},
	{
		"name": "Allistair Blanchard",
		"email": "aliquet.sem@imperdietnon.org",
		"phone": "(267) 914-0272",
		"country": "Greece",
		"id": 20
	},
	{
		"name": "Gareth H. Gaines",
		"email": "malesuada.fringilla.est@pellentesque.ca",
		"phone": "(129) 639-9746",
		"country": "Senegal",
		"id": 21
	},
	{
		"name": "Moses K. Wilson",
		"email": "libero.nec@aliquet.org",
		"phone": "(779) 856-6499",
		"country": "American Samoa",
		"id": 22
	},
	{
		"name": "Aaron Y. Thomas",
		"email": "magna@Inornaresagittis.edu",
		"phone": "(181) 346-2887",
		"country": "Algeria",
		"id": 23
	},
	{
		"name": "Iola Y. Hill",
		"email": "pede@dapibus.org",
		"phone": "(368) 273-1764",
		"country": "Iceland",
		"id": 24
	},
	{
		"name": "Belle K. Curry",
		"email": "Sed.auctor.odio@vitaesemperegestas.ca",
		"phone": "(509) 823-7457",
		"country": "Nigeria",
		"id": 25
	},
	{
		"name": "Cally W. Wilkinson",
		"email": "habitant@tellusPhasellus.org",
		"phone": "(955) 720-1683",
		"country": "United Arab Emirates",
		"id": 26
	},
	{
		"name": "Baker Small",
		"email": "fermentum.arcu@in.org",
		"phone": "(258) 493-9917",
		"country": "Martinique",
		"id": 27
	},
	{
		"name": "Erin Warren",
		"email": "semper@ipsumsodales.ca",
		"phone": "(838) 886-7299",
		"country": "Croatia",
		"id": 28
	},
	{
		"name": "Trevor M. Mccarthy",
		"email": "tellus@nislMaecenas.co.uk",
		"phone": "(341) 395-9296",
		"country": "Egypt",
		"id": 29
	},
	{
		"name": "Carson P. Wilkins",
		"email": "Nunc.sed@Sed.co.uk",
		"phone": "(655) 948-4013",
		"country": "France",
		"id": 30
	},
	{
		"name": "Deacon K. Hunter",
		"email": "diam@orciPhasellusdapibus.ca",
		"phone": "(348) 801-5940",
		"country": "Australia",
		"id": 31
	},
	{
		"name": "Alvin U. Hensley",
		"email": "semper.pretium.neque@Phasellus.co.uk",
		"phone": "(641) 878-5247",
		"country": "New Caledonia",
		"id": 32
	},
	{
		"name": "Matthew S. Larson",
		"email": "quam@tellus.org",
		"phone": "(928) 323-0255",
		"country": "Denmark",
		"id": 33
	},
	{
		"name": "Randall Boyd",
		"email": "et.netus.et@mifelis.ca",
		"phone": "(561) 370-6757",
		"country": "Algeria",
		"id": 34
	},
	{
		"name": "Aileen Rivers",
		"email": "cubilia.Curae.Phasellus@nondapibus.ca",
		"phone": "(138) 301-1342",
		"country": "Brazil",
		"id": 35
	},
	{
		"name": "Ciaran O. Fox",
		"email": "euismod.ac@CurabiturmassaVestibulum.com",
		"phone": "(840) 892-7635",
		"country": "Viet Nam",
		"id": 36
	},
	{
		"name": "Ariel Steele",
		"email": "tellus@eu.ca",
		"phone": "(606) 763-8051",
		"country": "Central African Republic",
		"id": 37
	},
	{
		"name": "Cody Cook",
		"email": "erat.eget@molestie.net",
		"phone": "(519) 885-3456",
		"country": "Singapore",
		"id": 38
	},
	{
		"name": "Cody J. Bird",
		"email": "et.magna.Praesent@nisl.net",
		"phone": "(254) 970-4482",
		"country": "Antigua and Barbuda",
		"id": 39
	},
	{
		"name": "Caldwell Pittman",
		"email": "neque@nonhendreritid.org",
		"phone": "(260) 572-4258",
		"country": "Tonga",
		"id": 40
	},
	{
		"name": "Demetrius C. Summers",
		"email": "a.scelerisque.sed@dui.org",
		"phone": "(535) 187-3417",
		"country": "French Guiana",
		"id": 41
	},
	{
		"name": "Tashya Romero",
		"email": "mattis.Cras@lacusEtiambibendum.org",
		"phone": "(167) 180-1342",
		"country": "Belgium",
		"id": 42
	},
	{
		"name": "Erich Kemp",
		"email": "egestas.ligula.Nullam@mollis.ca",
		"phone": "(556) 302-0438",
		"country": "Algeria",
		"id": 43
	},
	{
		"name": "Xantha Serrano",
		"email": "pellentesque.massa@pedenecante.org",
		"phone": "(658) 973-2535",
		"country": "Saint Barthélemy",
		"id": 44
	},
	{
		"name": "Lysandra Wall",
		"email": "dui@augue.org",
		"phone": "(989) 482-9333",
		"country": "Montserrat",
		"id": 45
	},
	{
		"name": "Arthur S. Chase",
		"email": "sed.turpis.nec@eratnequenon.org",
		"phone": "(235) 337-7804",
		"country": "Barbados",
		"id": 46
	},
	{
		"name": "Phoebe M. Underwood",
		"email": "quis@mollisvitae.ca",
		"phone": "(728) 405-0149",
		"country": "Colombia",
		"id": 47
	},
	{
		"name": "Cheryl Mayer",
		"email": "pretium@lacusCras.co.uk",
		"phone": "(134) 396-4052",
		"country": "Sint Maarten",
		"id": 48
	},
	{
		"name": "Hop Pennington",
		"email": "nunc.sed.libero@Duisvolutpat.com",
		"phone": "(730) 374-0075",
		"country": "Virgin Islands, British",
		"id": 49
	},
	{
		"name": "Tanek Watts",
		"email": "neque@mollis.com",
		"phone": "(169) 908-5382",
		"country": "Åland Islands",
		"id": 50
	},
	{
		"name": "Macy C. Britt",
		"email": "tincidunt.dui@asollicitudinorci.edu",
		"phone": "(694) 171-3836",
		"country": "Armenia",
		"id": 51
	},
	{
		"name": "Thane Franklin",
		"email": "nec.tempus.mauris@Curabitursedtortor.co.uk",
		"phone": "(809) 116-3017",
		"country": "Marshall Islands",
		"id": 52
	},
	{
		"name": "Xandra Frazier",
		"email": "interdum@temporerat.net",
		"phone": "(528) 371-5509",
		"country": "Saint Lucia",
		"id": 53
	},
	{
		"name": "Paloma Castaneda",
		"email": "odio.semper.cursus@a.net",
		"phone": "(336) 117-0001",
		"country": "Luxembourg",
		"id": 54
	},
	{
		"name": "Isaac S. Hoover",
		"email": "ac.arcu.Nunc@ametultriciessem.org",
		"phone": "(546) 599-7215",
		"country": "Pitcairn Islands",
		"id": 55
	},
	{
		"name": "Blaine X. Hutchinson",
		"email": "eu.ligula@diamProindolor.edu",
		"phone": "(818) 235-5481",
		"country": "Antarctica",
		"id": 56
	},
	{
		"name": "Simon G. Travis",
		"email": "aptent.taciti@Phasellusfermentumconvallis.com",
		"phone": "(204) 373-4130",
		"country": "Greece",
		"id": 57
	},
	{
		"name": "Belle R. Cook",
		"email": "a.purus@lorem.com",
		"phone": "(976) 563-6809",
		"country": "Burundi",
		"id": 58
	},
	{
		"name": "Alice L. Cameron",
		"email": "morbi.tristique@sitamet.ca",
		"phone": "(193) 216-1564",
		"country": "United States",
		"id": 59
	},
	{
		"name": "Hamilton R. Crawford",
		"email": "non.vestibulum@massaIntegervitae.com",
		"phone": "(887) 260-2963",
		"country": "Greenland",
		"id": 60
	},
	{
		"name": "Phelan P. Brock",
		"email": "Curabitur.egestas@odio.edu",
		"phone": "(325) 649-0926",
		"country": "Saint Lucia",
		"id": 61
	},
	{
		"name": "Tobias O. Ferrell",
		"email": "elit@mattisCraseget.org",
		"phone": "(990) 729-9113",
		"country": "Christmas Island",
		"id": 62
	},
	{
		"name": "Ruth Elliott",
		"email": "ultrices.a@lobortismaurisSuspendisse.edu",
		"phone": "(337) 493-1408",
		"country": "Benin",
		"id": 63
	},
	{
		"name": "Ori Knowles",
		"email": "sapien@afacilisis.ca",
		"phone": "(190) 241-9243",
		"country": "Ecuador",
		"id": 64
	},
	{
		"name": "Kennan G. Clay",
		"email": "mollis.dui@aodio.co.uk",
		"phone": "(491) 513-3601",
		"country": "Palau",
		"id": 65
	},
	{
		"name": "Austin Carney",
		"email": "tempus.scelerisque.lorem@non.edu",
		"phone": "(494) 399-7940",
		"country": "Austria",
		"id": 66
	},
	{
		"name": "Casey X. Petty",
		"email": "bibendum.sed@vulputatemauris.ca",
		"phone": "(896) 168-4153",
		"country": "Turkey",
		"id": 67
	},
	{
		"name": "Kitra Rojas",
		"email": "Donec.at@scelerisquesedsapien.ca",
		"phone": "(144) 777-5676",
		"country": "New Zealand",
		"id": 68
	},
	{
		"name": "Cailin Farrell",
		"email": "posuere.enim.nisl@ornaretortorat.org",
		"phone": "(809) 777-9679",
		"country": "Vanuatu",
		"id": 69
	},
	{
		"name": "Sawyer T. Rasmussen",
		"email": "Pellentesque@nisidictum.edu",
		"phone": "(798) 639-0736",
		"country": "Afghanistan",
		"id": 70
	},
	{
		"name": "Xander T. Marsh",
		"email": "felis.ullamcorper@sitamet.net",
		"phone": "(362) 500-6269",
		"country": "Central African Republic",
		"id": 71
	},
	{
		"name": "Elliott Johnston",
		"email": "consectetuer.cursus@nislQuisque.edu",
		"phone": "(223) 840-5867",
		"country": "Central African Republic",
		"id": 72
	},
	{
		"name": "Keelie Fleming",
		"email": "ac.orci.Ut@Sedauctorodio.ca",
		"phone": "(984) 480-8421",
		"country": "Haiti",
		"id": 73
	},
	{
		"name": "Latifah I. Walter",
		"email": "eget.varius.ultrices@sed.co.uk",
		"phone": "(144) 209-8878",
		"country": "Falkland Islands",
		"id": 74
	},
	{
		"name": "Xena H. Reed",
		"email": "tellus@fermentumconvallisligula.net",
		"phone": "(121) 955-8933",
		"country": "Cuba",
		"id": 75
	},
	{
		"name": "Cullen X. Jacobson",
		"email": "a.magna@velpede.com",
		"phone": "(725) 348-3533",
		"country": "Honduras",
		"id": 76
	},
	{
		"name": "Ivan Glass",
		"email": "dui.quis@Duismi.com",
		"phone": "(884) 689-2367",
		"country": "Guam",
		"id": 77
	},
	{
		"name": "Garrison C. Velasquez",
		"email": "Nulla.eu.neque@ullamcorper.org",
		"phone": "(550) 588-2005",
		"country": "Greenland",
		"id": 78
	},
	{
		"name": "Leonard E. Murphy",
		"email": "In.nec.orci@primisin.co.uk",
		"phone": "(137) 628-6700",
		"country": "Hong Kong",
		"id": 79
	},
	{
		"name": "Rajah Bonner",
		"email": "ante@aliquet.co.uk",
		"phone": "(794) 175-6055",
		"country": "Rwanda",
		"id": 80
	},
	{
		"name": "Kai K. Bowen",
		"email": "sed.pede.nec@volutpat.org",
		"phone": "(154) 697-1992",
		"country": "Bahamas",
		"id": 81
	},
	{
		"name": "Melyssa H. Woodard",
		"email": "odio@egestas.edu",
		"phone": "(630) 830-7058",
		"country": "Bahrain",
		"id": 82
	},
	{
		"name": "Arden Benson",
		"email": "aliquet.vel@quisdiam.edu",
		"phone": "(962) 351-0475",
		"country": "Cayman Islands",
		"id": 83
	},
	{
		"name": "Elton Brewer",
		"email": "pede.et.risus@dictumeueleifend.org",
		"phone": "(197) 224-8067",
		"country": "Kyrgyzstan",
		"id": 84
	},
	{
		"name": "Ross Singleton",
		"email": "purus.Nullam.scelerisque@posuereatvelit.org",
		"phone": "(227) 915-9256",
		"country": "Nauru",
		"id": 85
	},
	{
		"name": "Ethan M. Case",
		"email": "Praesent.interdum@Praesentluctus.net",
		"phone": "(429) 167-0230",
		"country": "Chile",
		"id": 86
	},
	{
		"name": "Marvin O. Dorsey",
		"email": "Integer.vitae.nibh@vulputateeu.edu",
		"phone": "(761) 997-3911",
		"country": "Croatia",
		"id": 87
	},
	{
		"name": "Mannix Franks",
		"email": "torquent.per.conubia@arcu.edu",
		"phone": "(424) 600-6448",
		"country": "Comoros",
		"id": 88
	},
	{
		"name": "Cyrus D. Keller",
		"email": "nibh@nonjustoProin.ca",
		"phone": "(630) 356-7018",
		"country": "Laos",
		"id": 89
	},
	{
		"name": "Rowan Boyer",
		"email": "at.velit@arcuetpede.com",
		"phone": "(308) 245-0035",
		"country": "Qatar",
		"id": 90
	},
	{
		"name": "Zachery Pennington",
		"email": "libero.Proin@atortor.ca",
		"phone": "(895) 519-0830",
		"country": "Kazakhstan",
		"id": 91
	},
	{
		"name": "Colleen Weiss",
		"email": "erat.neque@antelectus.edu",
		"phone": "(259) 707-4436",
		"country": "Sint Maarten",
		"id": 92
	},
	{
		"name": "Quinn Sykes",
		"email": "adipiscing.non.luctus@ipsumCurabiturconsequat.com",
		"phone": "(336) 384-1480",
		"country": "Taiwan",
		"id": 93
	},
	{
		"name": "Erin Figueroa",
		"email": "Donec.porttitor.tellus@amalesuada.org",
		"phone": "(405) 448-7214",
		"country": "Montserrat",
		"id": 94
	},
	{
		"name": "Serina A. Atkinson",
		"email": "tellus@lectus.net",
		"phone": "(771) 217-2308",
		"country": "Sierra Leone",
		"id": 95
	},
	{
		"name": "Dalton Conner",
		"email": "Quisque.tincidunt.pede@lobortisquispede.com",
		"phone": "(325) 564-4764",
		"country": "Burkina Faso",
		"id": 96
	},
	{
		"name": "Edan Wells",
		"email": "ipsum.dolor@Nuncsollicitudincommodo.net",
		"phone": "(839) 355-5661",
		"country": "Gambia",
		"id": 97
	},
	{
		"name": "Keane Tyler",
		"email": "a.enim@PraesentluctusCurabitur.co.uk",
		"phone": "(562) 202-5114",
		"country": "Antigua and Barbuda",
		"id": 98
	},
	{
		"name": "Harriet L. Nolan",
		"email": "cursus@Maecenas.com",
		"phone": "(986) 196-4177",
		"country": "Czech Republic",
		"id": 99
	},
	{
		"name": "Victoria D. Malone",
		"email": "dictum@loremtristiquealiquet.edu",
		"phone": "(506) 569-2600",
		"country": "Guatemala",
		"id": 100
	}
]